__init__.py
controller/controller.py
model/infrastructure.py
model/job.py
readers/compute_wait_time.py
readers/slurmreader.py
view/__init__.py
view/curses_multiwindow.py
view/slurm_list.py
view/slurm_viz.py
view/styles.py
view/utils.py
nodeocc-1.0.24.dist-info/METADATA
nodeocc-1.0.24.dist-info/WHEEL
nodeocc-1.0.24.dist-info/entry_points.txt
nodeocc-1.0.24.dist-info/top_level.txt
nodeocc-1.0.24.dist-info/RECORD
