Metadata-Version: 2.2
Name: nodeocc
Version: 1.0.24
Summary: TUI application for viewing the status of GPU allocations on a Slurm cluster
Author: Matteo Boschini
Maintainer: Lorenzo Bonicelli, Aniello Panariello
License: MIT
Project-URL: Repository, https://github.com/apanariello4/slurm_nodeocc
Keywords: Slurm,GPU,TUI,CLI,HPC,cluster,allocations,nodeocc
Classifier: Development Status :: 4 - Beta
Classifier: Environment :: Console :: Curses
Classifier: Programming Language :: Python :: 3
Requires-Python: >=3.9
Requires-Dist: pandas
Requires-Dist: numpy
Requires-Dist: psutil
